get_report_template/__init__.py
get_report_template/get_report_template.py
get_report_template/mobile_case_template.docx
get_report_template/pc_case_template.docx
get_report_template-0.0.7.dist-info/METADATA
get_report_template-0.0.7.dist-info/WHEEL
get_report_template-0.0.7.dist-info/entry_points.txt
get_report_template-0.0.7.dist-info/top_level.txt
get_report_template-0.0.7.dist-info/RECORD
