Metadata-Version: 2.1
Name: get-report-template
Version: 0.0.7
Home-page: https://github.com/jaytrairat/python-get-report-template
Author: JayTrairat
Author-email: jaytrairat@gmail.com
